[
  {
    "brand": "Givenchy",
    "href": "https://www.collectorsquare.com/en/bags/givenchy/antigona/givenchy-antigona-small-model-handbag-in-grey-grained-leather-380489.html",
    "price": 8819.9,
    "trends": [
      {
        "date": "2024-05-18",
        "price": 8819.9
      },
      {
        "date": "2024-04-13",
        "price": 9680.0
      },
      {
        "date": "2024-03-23",
        "price": 9680.0
      }
    ],
    "title": "Givenchy Antigona small model handbag in grey grained leather",
    "like": 0,
    "source": "CollectorSquare",
    "url": "https://www.collectorsquare.com/en/bags/givenchy/antigona/givenchy-antigona-small-model-handbag-in-grey-grained-leather-380489.html",
    "id": "collectorsquare-380489",
    "productId": "380489",
    "currency": "HKD",
    "image": "https://medias.collectorsquare.com/images/products/380489/thumb-givenchy-antigona-small-model-handbag-in-grey-grained-leather.jpg",
    "condition": "Pre-Owned",
    "collection": "antigona",
    "color": "grey",
    "material": "leather",
    "category": "handbag",
    "folder": "bag/givenchy/antigona",
    "size": "small"
  },
  {
    "brand": "Givenchy",
    "href": "https://www.collectorsquare.com/en/bags/givenchy/lucrezia/handbag-in-purple-leather-368443.html",
    "price": 5351.4,
    "trends": [
      {
        "date": "2024-05-18",
        "price": 5351.4
      },
      {
        "date": "2024-04-13",
        "price": 6170.0
      },
      {
        "date": "2024-03-23",
        "price": 6170.0
      }
    ],
    "title": "Handbag in purple leather",
    "like": 0,
    "source": "CollectorSquare",
    "url": "https://www.collectorsquare.com/en/bags/givenchy/lucrezia/handbag-in-purple-leather-368443.html",
    "id": "collectorsquare-368443",
    "productId": "368443",
    "currency": "HKD",
    "image": "https://medias.collectorsquare.com/images/products/368443/thumb-handbag-in-purple-leather.jpg",
    "condition": "Pre-Owned",
    "collection": "lucrezia",
    "color": "purple",
    "material": "leather",
    "category": "handbag",
    "folder": "bag/givenchy/lucrezia",
    "size": null
  },
  {
    "brand": "Givenchy",
    "href": "https://www.collectorsquare.com/en/bags/givenchy/antigona/givenchy-antigona-medium-model-handbag-in-red-leather-350362.html",
    "price": 8225.3,
    "trends": [
      {
        "date": "2024-05-18",
        "price": 8225.3
      },
      {
        "date": "2024-04-13",
        "price": 9100.0
      },
      {
        "date": "2024-03-23",
        "price": 9100.0
      }
    ],
    "title": "Givenchy Antigona medium model handbag in red leather",
    "like": 0,
    "source": "CollectorSquare",
    "url": "https://www.collectorsquare.com/en/bags/givenchy/antigona/givenchy-antigona-medium-model-handbag-in-red-leather-350362.html",
    "id": "collectorsquare-350362",
    "productId": "350362",
    "currency": "HKD",
    "image": "https://medias.collectorsquare.com/images/products/350362/thumb-givenchy-antigona-medium-model-handbag-in-red-leather.jpg",
    "condition": "Pre-Owned",
    "collection": "antigona",
    "color": "red",
    "material": "leather",
    "category": "handbag",
    "folder": "bag/givenchy/antigona",
    "size": "medium"
  },
  {
    "brand": "Givenchy",
    "href": "https://www.collectorsquare.com/en/bags/givenchy/nightingale/givenchy-nightingale-24-hours-bag-in-black-suede-360967.html",
    "price": 6144.2,
    "trends": [
      {
        "date": "2024-05-18",
        "price": 6144.2
      },
      {
        "date": "2024-04-13",
        "price": 6990.0
      },
      {
        "date": "2024-03-23",
        "price": 6990.0
      }
    ],
    "title": "Givenchy Nightingale 24 hours bag in black suede",
    "like": 0,
    "source": "CollectorSquare",
    "url": "https://www.collectorsquare.com/en/bags/givenchy/nightingale/givenchy-nightingale-24-hours-bag-in-black-suede-360967.html",
    "id": "collectorsquare-360967",
    "productId": "360967",
    "currency": "HKD",
    "image": "https://medias.collectorsquare.com/images/products/360967/thumb-givenchy-nightingale-24-hours-bag-in-black-suede.jpg",
    "condition": "Pre-Owned",
    "collection": "nightingale",
    "color": "black",
    "material": "suede",
    "category": "handbag",
    "folder": "bag/givenchy/nightingale",
    "size": null
  },
  {
    "brand": "Givenchy",
    "href": "https://www.collectorsquare.com/en/bags/givenchy/antigona/givenchy-antigona-handbag-in-black-leather-390898.html",
    "price": 9612.7,
    "trends": [
      {
        "date": "2024-05-18",
        "price": 9612.7
      },
      {
        "date": "2024-04-13",
        "price": 10500.0
      },
      {
        "date": "2024-03-23",
        "price": 10500.0
      }
    ],
    "title": "Givenchy Antigona medium model handbag in black leather",
    "like": 0,
    "source": "CollectorSquare",
    "url": "https://www.collectorsquare.com/en/bags/givenchy/antigona/givenchy-antigona-handbag-in-black-leather-390898.html",
    "id": "collectorsquare-390898",
    "productId": "390898",
    "currency": "HKD",
    "image": "https://medias.collectorsquare.com/images/products/390898/thumb-givenchy-antigona-medium-model-handbag-in-black-leather.jpg",
    "condition": "Pre-Owned",
    "collection": "antigona",
    "color": "black",
    "material": "leather",
    "category": "handbag",
    "folder": "bag/givenchy/antigona",
    "size": "medium"
  },
  {
    "brand": "Givenchy",
    "href": "https://www.collectorsquare.com/en/bags/givenchy/antigona/givenchy-antigona-weekend-bag-in-gold-smooth-leather-398652.html",
    "price": 8919.0,
    "trends": [
      {
        "date": "2024-05-18",
        "price": 8919.0
      },
      {
        "date": "2024-04-13",
        "price": 9770.0
      },
      {
        "date": "2024-03-23",
        "price": 9770.0
      }
    ],
    "title": "Givenchy Antigona weekend bag in gold smooth leather",
    "like": 0,
    "source": "CollectorSquare",
    "url": "https://www.collectorsquare.com/en/bags/givenchy/antigona/givenchy-antigona-weekend-bag-in-gold-smooth-leather-398652.html",
    "id": "collectorsquare-398652",
    "productId": "398652",
    "currency": "HKD",
    "image": "https://medias.collectorsquare.com/images/products/398652/thumb-givenchy-antigona-weekend-bag-in-gold-smooth-leather.jpg",
    "condition": "Pre-Owned",
    "collection": "antigona",
    "color": "brown",
    "material": "leather",
    "category": "travel bag",
    "folder": "bag/givenchy/antigona",
    "size": null
  },
  {
    "brand": "Givenchy",
    "href": "https://www.collectorsquare.com/en/bags/givenchy/pandora/givenchy-pandora-shoulder-bag-in-black-rabbit-furr-and-black-leather-406486.html",
    "price": 4360.4,
    "trends": [
      {
        "date": "2024-05-18",
        "price": 4360.4
      },
      {
        "date": "2024-04-13",
        "price": 5200.0
      },
      {
        "date": "2024-03-23",
        "price": 5200.0
      }
    ],
    "title": "Givenchy Pandora shoulder bag in black rabbit furr and black leather",
    "like": 0,
    "source": "CollectorSquare",
    "url": "https://www.collectorsquare.com/en/bags/givenchy/pandora/givenchy-pandora-shoulder-bag-in-black-rabbit-furr-and-black-leather-406486.html",
    "id": "collectorsquare-406486",
    "productId": "406486",
    "currency": "HKD",
    "image": "https://medias.collectorsquare.com/images/products/406486/thumb-givenchy-pandora-shoulder-bag-in-black-rabbit-furr-and-black-leather.jpg",
    "condition": "Pre-Owned",
    "collection": "pandora",
    "color": "black",
    "material": "fur",
    "category": "shoulder bag",
    "folder": "bag/givenchy/pandora",
    "size": null
  },
  {
    "brand": "Givenchy",
    "href": "https://www.collectorsquare.com/en/bags/givenchy/antigona/givenchy-antigona-handbag-in-brown-and-black-leather-400809.html",
    "price": 6937.0,
    "trends": [
      {
        "date": "2024-05-18",
        "price": 6937.0
      },
      {
        "date": "2024-04-13",
        "price": 7810.0
      },
      {
        "date": "2024-03-23",
        "price": 7810.0
      }
    ],
    "title": "Givenchy Antigona medium model handbag in brown and black leather",
    "like": 0,
    "source": "CollectorSquare",
    "url": "https://www.collectorsquare.com/en/bags/givenchy/antigona/givenchy-antigona-handbag-in-brown-and-black-leather-400809.html",
    "id": "collectorsquare-400809",
    "productId": "400809",
    "currency": "HKD",
    "image": "https://medias.collectorsquare.com/images/products/400809/thumb-givenchy-antigona-medium-model-handbag-in-brown-and-black-leather.jpg",
    "condition": "Pre-Owned",
    "collection": "antigona",
    "color": "black",
    "material": "leather",
    "category": "handbag",
    "folder": "bag/givenchy/antigona",
    "size": "medium"
  },
  {
    "brand": "Givenchy",
    "href": "https://www.collectorsquare.com/en/bags/givenchy/antigona/givenchy-antigona-handbag-in-black-leather-404838.html",
    "price": 6937.0,
    "trends": [
      {
        "date": "2024-05-18",
        "price": 6937.0
      },
      {
        "date": "2024-04-13",
        "price": 7810.0
      },
      {
        "date": "2024-03-23",
        "price": 7810.0
      }
    ],
    "title": "Givenchy Antigona handbag in black leather",
    "like": 0,
    "source": "CollectorSquare",
    "url": "https://www.collectorsquare.com/en/bags/givenchy/antigona/givenchy-antigona-handbag-in-black-leather-404838.html",
    "id": "collectorsquare-404838",
    "productId": "404838",
    "currency": "HKD",
    "image": "https://medias.collectorsquare.com/images/products/404838/thumb-givenchy-antigona-handbag-in-black-leather.jpg",
    "condition": "Pre-Owned",
    "collection": "antigona",
    "color": "black",
    "material": "leather",
    "category": "handbag",
    "folder": "bag/givenchy/antigona",
    "size": null
  },
  {
    "brand": "Givenchy",
    "href": "https://www.collectorsquare.com/en/bags/givenchy/antigona/givenchy-antigona-medium-model-bag-worn-on-the-shoulder-or-carried-in-the-hand-in-black-leather-399294.html",
    "price": 10207.3,
    "trends": [
      {
        "date": "2024-05-18",
        "price": 10207.3
      },
      {
        "date": "2024-04-13",
        "price": 11070.0
      },
      {
        "date": "2024-03-23",
        "price": 11070.0
      }
    ],
    "title": "Givenchy Antigona medium model bag worn on the shoulder or carried in the hand in black leather",
    "like": 0,
    "source": "CollectorSquare",
    "url": "https://www.collectorsquare.com/en/bags/givenchy/antigona/givenchy-antigona-medium-model-bag-worn-on-the-shoulder-or-carried-in-the-hand-in-black-leather-399294.html",
    "id": "collectorsquare-399294",
    "productId": "399294",
    "currency": "HKD",
    "image": "https://medias.collectorsquare.com/images/products/399294/thumb-givenchy-antigona-medium-model-bag-worn-on-the-shoulder-or-carried-in-the-hand-in-black-leather.jpg",
    "condition": "Pre-Owned",
    "collection": "antigona",
    "color": "black",
    "material": "leather",
    "category": "handbag",
    "folder": "bag/givenchy/antigona",
    "size": "medium"
  },
  {
    "brand": "Givenchy",
    "href": "https://www.collectorsquare.com/en/bags/givenchy/antigona/givenchy-antigona-small-model-handbag-in-turquoise-leather-352842.html",
    "price": 6144.2,
    "trends": [
      {
        "date": "2024-05-18",
        "price": 6144.2
      },
      {
        "date": "2024-04-13",
        "price": 7030.0
      },
      {
        "date": "2024-03-23",
        "price": 7030.0
      }
    ],
    "title": "Givenchy Antigona small model handbag in turquoise leather",
    "like": 0,
    "source": "CollectorSquare",
    "url": "https://www.collectorsquare.com/en/bags/givenchy/antigona/givenchy-antigona-small-model-handbag-in-turquoise-leather-352842.html",
    "id": "collectorsquare-352842",
    "productId": "352842",
    "currency": "HKD",
    "image": "https://medias.collectorsquare.com/images/products/352842/thumb-givenchy-antigona-small-model-handbag-in-turquoise-leather.jpg",
    "condition": "Pre-Owned",
    "collection": "antigona",
    "color": "blue",
    "material": "leather",
    "category": "handbag",
    "folder": "bag/givenchy/antigona",
    "size": "small"
  },
  {
    "brand": "Givenchy",
    "href": "https://www.collectorsquare.com/en/bags/givenchy/antigona/givenchy-antigona-tote-shopping-bag-in-black-coated-canvas-and-pink-leather-382811.html",
    "price": 5351.4,
    "trends": [
      {
        "date": "2024-05-18",
        "price": 5351.4
      },
      {
        "date": "2024-04-13",
        "price": 6170.0
      },
      {
        "date": "2024-03-23",
        "price": 6170.0
      }
    ],
    "title": "Givenchy Antigona Tote shopping bag in black coated canvas and pink leather",
    "like": 0,
    "source": "CollectorSquare",
    "url": "https://www.collectorsquare.com/en/bags/givenchy/antigona/givenchy-antigona-tote-shopping-bag-in-black-coated-canvas-and-pink-leather-382811.html",
    "id": "collectorsquare-382811",
    "productId": "382811",
    "currency": "HKD",
    "image": "https://medias.collectorsquare.com/images/products/382811/thumb-givenchy-antigona-tote-shopping-bag-in-black-coated-canvas-and-pink-leather.jpg",
    "condition": "Pre-Owned",
    "collection": "antigona",
    "color": "black",
    "material": "canvas",
    "category": "tote",
    "folder": "bag/givenchy/antigona",
    "size": null
  },
  {
    "brand": "Givenchy",
    "href": "https://www.collectorsquare.com/en/bags/givenchy/antigona/givenchy-antigona-handbag-in-black-leather-405139.html",
    "price": 8027.1,
    "trends": [
      {
        "date": "2024-05-18",
        "price": 8027.1
      },
      {
        "date": "2024-04-13",
        "price": 8870.0
      },
      {
        "date": "2024-03-23",
        "price": 8870.0
      }
    ],
    "title": "Givenchy Antigona small model handbag in black leather",
    "like": 0,
    "source": "CollectorSquare",
    "url": "https://www.collectorsquare.com/en/bags/givenchy/antigona/givenchy-antigona-handbag-in-black-leather-405139.html",
    "id": "collectorsquare-405139",
    "productId": "405139",
    "currency": "HKD",
    "image": "https://medias.collectorsquare.com/images/products/405139/thumb-givenchy-antigona-small-model-handbag-in-black-leather.jpg",
    "condition": "Pre-Owned",
    "collection": "antigona",
    "color": "black",
    "material": "leather",
    "category": "handbag",
    "folder": "bag/givenchy/antigona",
    "size": "small"
  },
  {
    "brand": "Givenchy",
    "href": "https://www.collectorsquare.com/en/bags/givenchy/antigona/givenchy-antigona-handbag-in-fuchsia-leather-403911.html",
    "price": 7729.8,
    "trends": [
      {
        "date": "2024-05-18",
        "price": 7729.8
      },
      {
        "date": "2024-04-13",
        "price": 8620.0
      },
      {
        "date": "2024-03-23",
        "price": 8620.0
      }
    ],
    "title": "Givenchy Antigona medium model handbag in fuchsia leather",
    "like": 0,
    "source": "CollectorSquare",
    "url": "https://www.collectorsquare.com/en/bags/givenchy/antigona/givenchy-antigona-handbag-in-fuchsia-leather-403911.html",
    "id": "collectorsquare-403911",
    "productId": "403911",
    "currency": "HKD",
    "image": "https://medias.collectorsquare.com/images/products/403911/thumb-givenchy-antigona-medium-model-handbag-in-fuchsia-leather.jpg",
    "condition": "Pre-Owned",
    "collection": "antigona",
    "color": "purple",
    "material": "leather",
    "category": "handbag",
    "folder": "bag/givenchy/antigona",
    "size": "medium"
  },
  {
    "brand": "Givenchy",
    "href": "https://www.collectorsquare.com/en/bags/givenchy/antigona/givenchy-antigona-handbag-in-black-leather-400833.html",
    "price": 8027.1,
    "trends": [
      {
        "date": "2024-05-18",
        "price": 8027.1
      },
      {
        "date": "2024-04-13",
        "price": 8870.0
      },
      {
        "date": "2024-03-23",
        "price": 8870.0
      }
    ],
    "title": "Givenchy Antigona medium model handbag in black leather",
    "like": 0,
    "source": "CollectorSquare",
    "url": "https://www.collectorsquare.com/en/bags/givenchy/antigona/givenchy-antigona-handbag-in-black-leather-400833.html",
    "id": "collectorsquare-400833",
    "productId": "400833",
    "currency": "HKD",
    "image": "https://medias.collectorsquare.com/images/products/400833/thumb-givenchy-antigona-medium-model-handbag-in-black-leather.jpg",
    "condition": "Pre-Owned",
    "collection": "antigona",
    "color": "black",
    "material": "leather",
    "category": "handbag",
    "folder": "bag/givenchy/antigona",
    "size": "medium"
  },
  {
    "brand": "Givenchy",
    "href": "https://www.collectorsquare.com/en/bags/givenchy/infinity/givenchy-infinity-backpack-in-white-canvas-400671.html",
    "price": 4459.5,
    "trends": [
      {
        "date": "2024-05-18",
        "price": 4459.5
      },
      {
        "date": "2024-04-13",
        "price": 5360.0
      },
      {
        "date": "2024-03-23",
        "price": 5360.0
      }
    ],
    "title": "Givenchy Infinity backpack in white canvas",
    "like": 0,
    "source": "CollectorSquare",
    "url": "https://www.collectorsquare.com/en/bags/givenchy/infinity/givenchy-infinity-backpack-in-white-canvas-400671.html",
    "id": "collectorsquare-400671",
    "productId": "400671",
    "currency": "HKD",
    "image": "https://medias.collectorsquare.com/images/products/400671/thumb-givenchy-infinity-backpack-in-white-canvas.jpg",
    "condition": "Pre-Owned",
    "collection": "infinity",
    "color": "white",
    "material": "canvas",
    "category": "backpack",
    "folder": "bag/givenchy/infinity",
    "size": null
  },
  {
    "brand": "Givenchy",
    "href": "https://www.collectorsquare.com/en/bags/givenchy/pandora/givenchy-pandora-shoulder-bag-in-blue-grained-leather-391469.html",
    "price": 6441.5,
    "trends": [
      {
        "date": "2024-05-18",
        "price": 6441.5
      },
      {
        "date": "2024-04-13",
        "price": 7320.0
      },
      {
        "date": "2024-03-23",
        "price": 7320.0
      }
    ],
    "title": "Givenchy Pandora shoulder bag in blue grained leather",
    "like": 0,
    "source": "CollectorSquare",
    "url": "https://www.collectorsquare.com/en/bags/givenchy/pandora/givenchy-pandora-shoulder-bag-in-blue-grained-leather-391469.html",
    "id": "collectorsquare-391469",
    "productId": "391469",
    "currency": "HKD",
    "image": "https://medias.collectorsquare.com/images/products/391469/thumb-givenchy-pandora-shoulder-bag-in-blue-grained-leather.jpg",
    "condition": "Pre-Owned",
    "collection": "pandora",
    "color": "blue",
    "material": "leather",
    "category": "handbag",
    "folder": "bag/givenchy/pandora",
    "size": null
  },
  {
    "brand": "Givenchy",
    "href": "https://www.collectorsquare.com/en/bags/givenchy/infinity/givenchy-infinity-shoulder-bag-in-burgundy-leather-395022.html",
    "price": 7333.400000000001,
    "trends": [
      {
        "date": "2024-05-18",
        "price": 7333.400000000001
      },
      {
        "date": "2024-04-13",
        "price": 7120.0
      },
      {
        "date": "2024-03-23",
        "price": 8130.0
      }
    ],
    "title": "Givenchy Infinity shoulder bag in burgundy leather",
    "like": 0,
    "source": "CollectorSquare",
    "url": "https://www.collectorsquare.com/en/bags/givenchy/infinity/givenchy-infinity-shoulder-bag-in-burgundy-leather-395022.html",
    "id": "collectorsquare-395022",
    "productId": "395022",
    "currency": "HKD",
    "image": "https://medias.collectorsquare.com/images/products/395022/thumb-givenchy-infinity-shoulder-bag-in-burgundy-leather.jpg",
    "condition": "Pre-Owned",
    "collection": "infinity",
    "color": "burgundy",
    "material": "leather",
    "category": "shoulder bag",
    "folder": "bag/givenchy/infinity",
    "size": null
  },
  {
    "brand": "Givenchy",
    "href": "https://www.collectorsquare.com/en/bags/givenchy/pandora/givenchy-pandora-medium-model-shoulder-bag-in-grey-and-beige-python-359970.html",
    "price": 6144.2,
    "trends": [
      {
        "date": "2024-05-18",
        "price": 6144.2
      },
      {
        "date": "2024-04-13",
        "price": 7010.0
      },
      {
        "date": "2024-03-23",
        "price": 7010.0
      }
    ],
    "title": "Givenchy Pandora medium model shoulder bag in grey and beige python",
    "like": 0,
    "source": "CollectorSquare",
    "url": "https://www.collectorsquare.com/en/bags/givenchy/pandora/givenchy-pandora-medium-model-shoulder-bag-in-grey-and-beige-python-359970.html",
    "id": "collectorsquare-359970",
    "productId": "359970",
    "currency": "HKD",
    "image": "https://medias.collectorsquare.com/images/products/359970/thumb-givenchy-pandora-medium-model-shoulder-bag-in-grey-and-beige-python.jpg",
    "condition": "Pre-Owned",
    "collection": "pandora",
    "color": "grey",
    "material": "python",
    "category": "shoulder bag",
    "folder": "bag/givenchy/pandora",
    "size": "medium"
  },
  {
    "brand": "Givenchy",
    "href": "https://www.collectorsquare.com/en/bags/givenchy/antigona/givenchy-antigona-bag-worn-on-the-shoulder-or-carried-in-the-hand-in-black-leather-401753.html",
    "price": 8027.1,
    "trends": [
      {
        "date": "2024-05-18",
        "price": 8027.1
      },
      {
        "date": "2024-04-13",
        "price": 8870.0
      },
      {
        "date": "2024-03-23",
        "price": 8870.0
      }
    ],
    "title": "Givenchy Antigona bag worn on the shoulder or carried in the hand in black leather",
    "like": 0,
    "source": "CollectorSquare",
    "url": "https://www.collectorsquare.com/en/bags/givenchy/antigona/givenchy-antigona-bag-worn-on-the-shoulder-or-carried-in-the-hand-in-black-leather-401753.html",
    "id": "collectorsquare-401753",
    "productId": "401753",
    "currency": "HKD",
    "image": "https://medias.collectorsquare.com/images/products/401753/thumb-givenchy-antigona-bag-worn-on-the-shoulder-or-carried-in-the-hand-in-black-leather.jpg",
    "condition": "Pre-Owned",
    "collection": "antigona",
    "color": "black",
    "material": "leather",
    "category": "shoulder bag",
    "folder": "bag/givenchy/antigona",
    "size": null
  },
  {
    "brand": "Givenchy",
    "href": "https://www.collectorsquare.com/en/bags/givenchy/pandora/givenchy-pandora-shoulder-bag-in-black-leather-408155.html",
    "price": 5846.9,
    "trends": [
      {
        "date": "2024-05-18",
        "price": 5846.9
      },
      {
        "date": "2024-04-13",
        "price": 6750.0
      },
      {
        "date": "2024-03-23",
        "price": 6750.0
      }
    ],
    "title": "Givenchy Pandora shoulder bag in black leather",
    "like": 0,
    "source": "CollectorSquare",
    "url": "https://www.collectorsquare.com/en/bags/givenchy/pandora/givenchy-pandora-shoulder-bag-in-black-leather-408155.html",
    "id": "collectorsquare-408155",
    "productId": "408155",
    "currency": "HKD",
    "image": "https://medias.collectorsquare.com/images/products/408155/thumb-givenchy-pandora-shoulder-bag-in-black-leather.jpg",
    "condition": "Pre-Owned",
    "collection": "pandora",
    "material": "leather",
    "category": "shoulder bag",
    "folder": "bag/givenchy/pandora",
    "size": null,
    "color": "black"
  },
  {
    "brand": "Givenchy",
    "href": "https://www.collectorsquare.com/en/bags/givenchy/gv3/givenchy-gv3-handbag-in-raspberry-pink-leather-and-raspberry-pink-suede-391503.html",
    "price": 7234.3,
    "trends": [
      {
        "date": "2024-05-18",
        "price": 7234.3
      },
      {
        "date": "2024-04-13",
        "price": 8050.0
      },
      {
        "date": "2024-03-23",
        "price": 8050.0
      }
    ],
    "title": "Givenchy GV3 handbag in raspberry pink leather and raspberry pink suede",
    "like": 0,
    "source": "CollectorSquare",
    "url": "https://www.collectorsquare.com/en/bags/givenchy/gv3/givenchy-gv3-handbag-in-raspberry-pink-leather-and-raspberry-pink-suede-391503.html",
    "id": "collectorsquare-391503",
    "productId": "391503",
    "currency": "HKD",
    "image": "https://medias.collectorsquare.com/images/products/391503/thumb-givenchy-gv3-handbag-in-raspberry-pink-leather-and-raspberry-pink-suede.jpg",
    "condition": "Pre-Owned",
    "collection": "gv3",
    "color": "pink",
    "material": "suede",
    "category": "shoulder bag",
    "folder": "bag/givenchy/gv3",
    "size": null
  },
  {
    "brand": "Givenchy",
    "href": "https://www.collectorsquare.com/en/bags/givenchy/antigona/givenchy-antigona-small-model-handbag-in-pink-leather-395312.html",
    "price": 8027.1,
    "trends": [
      {
        "date": "2024-05-18",
        "price": 8027.1
      },
      {
        "date": "2024-04-13",
        "price": 8870.0
      },
      {
        "date": "2024-03-23",
        "price": 8870.0
      }
    ],
    "title": "Givenchy Antigona small model handbag in pink leather",
    "like": 0,
    "source": "CollectorSquare",
    "url": "https://www.collectorsquare.com/en/bags/givenchy/antigona/givenchy-antigona-small-model-handbag-in-pink-leather-395312.html",
    "id": "collectorsquare-395312",
    "productId": "395312",
    "currency": "HKD",
    "image": "https://medias.collectorsquare.com/images/products/395312/thumb-givenchy-antigona-small-model-handbag-in-pink-leather.jpg",
    "condition": "Pre-Owned",
    "collection": "antigona",
    "color": "pink",
    "material": "leather",
    "category": "shoulder bag",
    "folder": "bag/givenchy/antigona",
    "size": "small"
  },
  {
    "brand": "Givenchy",
    "href": "https://www.collectorsquare.com/en/bags/givenchy/nightingale/givenchy-nightingale-handbag-in-taupe-leather-406089.html",
    "price": 5351.4,
    "trends": [
      {
        "date": "2024-05-18",
        "price": 5351.4
      },
      {
        "date": "2024-04-13",
        "price": 6170.0
      },
      {
        "date": "2024-03-23",
        "price": 6170.0
      }
    ],
    "title": "Givenchy Nightingale handbag in taupe leather",
    "like": 0,
    "source": "CollectorSquare",
    "url": "https://www.collectorsquare.com/en/bags/givenchy/nightingale/givenchy-nightingale-handbag-in-taupe-leather-406089.html",
    "id": "collectorsquare-406089",
    "productId": "406089",
    "currency": "HKD",
    "image": "https://medias.collectorsquare.com/images/products/406089/thumb-givenchy-nightingale-handbag-in-taupe-leather.jpg",
    "condition": "Pre-Owned",
    "collection": "nightingale",
    "color": "brown",
    "material": "leather",
    "category": "handbag",
    "folder": "bag/givenchy/nightingale",
    "size": null
  },
  {
    "brand": "Givenchy",
    "href": "https://www.collectorsquare.com/en/bags/givenchy/pandora/givenchy-pandora-handbag-in-black-leather-408078.html",
    "price": 5549.6,
    "trends": [
      {
        "date": "2024-05-18",
        "price": 5549.6
      },
      {
        "date": "2024-04-13",
        "price": 6420.0
      },
      {
        "date": "2024-03-23",
        "price": 6420.0
      }
    ],
    "title": "Givenchy Pandora handbag in black leather",
    "like": 0,
    "source": "CollectorSquare",
    "url": "https://www.collectorsquare.com/en/bags/givenchy/pandora/givenchy-pandora-handbag-in-black-leather-408078.html",
    "id": "collectorsquare-408078",
    "productId": "408078",
    "currency": "HKD",
    "image": "https://medias.collectorsquare.com/images/products/408078/thumb-givenchy-pandora-handbag-in-black-leather.jpg",
    "condition": "Pre-Owned",
    "collection": "pandora",
    "color": "black",
    "material": "leather",
    "category": "handbag",
    "folder": "bag/givenchy/pandora",
    "size": null
  },
  {
    "brand": "Givenchy",
    "href": "https://www.collectorsquare.com/en/bags/givenchy/gv3/givenchy-gv3-small-model-shoulder-bag-in-red-quilted-leather-403372.html",
    "price": 4756.8,
    "trends": [
      {
        "date": "2024-05-18",
        "price": 4756.8
      },
      {
        "date": "2024-04-13",
        "price": 5600.0
      },
      {
        "date": "2024-03-23",
        "price": 5600.0
      }
    ],
    "title": "Givenchy GV3 small model shoulder bag in red quilted leather",
    "like": 0,
    "source": "CollectorSquare",
    "url": "https://www.collectorsquare.com/en/bags/givenchy/gv3/givenchy-gv3-small-model-shoulder-bag-in-red-quilted-leather-403372.html",
    "id": "collectorsquare-403372",
    "productId": "403372",
    "currency": "HKD",
    "image": "https://medias.collectorsquare.com/images/products/403372/thumb-givenchy-gv3-small-model-shoulder-bag-in-red-quilted-leather.jpg",
    "condition": "Pre-Owned",
    "collection": "gv3",
    "color": "red",
    "material": "leather",
    "category": "shoulder bag",
    "folder": "bag/givenchy/gv3",
    "size": "small"
  },
  {
    "brand": "Givenchy",
    "href": "https://www.collectorsquare.com/en/bags/givenchy/pandora/givenchy-pandora-medium-model-shoulder-bag-in-black-leather-361147.html",
    "price": 9216.3,
    "trends": [
      {
        "date": "2024-05-18",
        "price": 9216.3
      }
    ],
    "title": "Givenchy Pandora medium model shoulder bag in black leather",
    "like": 0,
    "source": "CollectorSquare",
    "url": "https://www.collectorsquare.com/en/bags/givenchy/pandora/givenchy-pandora-medium-model-shoulder-bag-in-black-leather-361147.html",
    "id": "collectorsquare-361147",
    "productId": "361147",
    "currency": "HKD",
    "image": "https://medias.collectorsquare.com/images/products/361147/thumb-givenchy-pandora-medium-model-shoulder-bag-in-black-leather.jpg",
    "condition": "Pre-Owned",
    "collection": "pandora",
    "color": "black",
    "material": "leather",
    "category": "shoulder bag",
    "folder": "bag/givenchy/pandora",
    "size": "medium"
  },
  {
    "brand": "Givenchy",
    "href": "https://www.collectorsquare.com/en/bags/givenchy/antigona/givenchy-antigona-small-model-handbag-in-grey-grained-leather-379916.html",
    "price": 8522.6,
    "trends": [
      {
        "date": "2024-05-18",
        "price": 8522.6
      },
      {
        "date": "2024-04-13",
        "price": 9390.0
      },
      {
        "date": "2024-03-23",
        "price": 9390.0
      }
    ],
    "title": "Givenchy Antigona small model handbag in grey grained leather",
    "like": 0,
    "source": "CollectorSquare",
    "url": "https://www.collectorsquare.com/en/bags/givenchy/antigona/givenchy-antigona-small-model-handbag-in-grey-grained-leather-379916.html",
    "id": "collectorsquare-379916",
    "productId": "379916",
    "currency": "HKD",
    "image": "https://medias.collectorsquare.com/images/products/379916/thumb-givenchy-antigona-small-model-handbag-in-grey-grained-leather.jpg",
    "condition": "Pre-Owned",
    "collection": "antigona",
    "color": "grey",
    "material": "leather",
    "category": "handbag",
    "folder": "bag/givenchy/antigona",
    "size": "small"
  },
  {
    "brand": "Givenchy",
    "href": "https://www.collectorsquare.com/en/bags/givenchy/pandora/givenchy-pandora-shoulder-bag-in-black-leather-and-black-foal-366431.html",
    "price": 3666.7000000000003,
    "trends": [
      {
        "date": "2024-05-18",
        "price": 3666.7000000000003
      },
      {
        "date": "2024-04-13",
        "price": 3910.0
      },
      {
        "date": "2024-03-23",
        "price": 3910.0
      }
    ],
    "title": "Givenchy Pandora shoulder bag in black leather and black foal",
    "like": 0,
    "source": "CollectorSquare",
    "url": "https://www.collectorsquare.com/en/bags/givenchy/pandora/givenchy-pandora-shoulder-bag-in-black-leather-and-black-foal-366431.html",
    "id": "collectorsquare-366431",
    "productId": "366431",
    "currency": "HKD",
    "image": "https://medias.collectorsquare.com/images/products/366431/thumb-givenchy-pandora-shoulder-bag-in-black-leather-and-black-foal.jpg",
    "condition": "Pre-Owned",
    "collection": "pandora",
    "color": "black",
    "material": "leather",
    "category": "shoulder bag",
    "folder": "bag/givenchy/pandora",
    "size": null
  },
  {
    "brand": "Givenchy",
    "href": "https://www.collectorsquare.com/en/bags/givenchy/antigona/givenchy-antigona-medium-model-bag-worn-on-the-shoulder-or-carried-in-the-hand-in-black-grained-leather-369858.html",
    "price": 10207.3,
    "trends": [
      {
        "date": "2024-05-18",
        "price": 10207.3
      },
      {
        "date": "2024-04-13",
        "price": 9150.0
      },
      {
        "date": "2024-03-23",
        "price": 9150.0
      }
    ],
    "title": "Givenchy Antigona medium model bag worn on the shoulder or carried in the hand in black grained leather",
    "like": 0,
    "source": "CollectorSquare",
    "url": "https://www.collectorsquare.com/en/bags/givenchy/antigona/givenchy-antigona-medium-model-bag-worn-on-the-shoulder-or-carried-in-the-hand-in-black-grained-leather-369858.html",
    "id": "collectorsquare-369858",
    "productId": "369858",
    "currency": "HKD",
    "image": "https://medias.collectorsquare.com/images/products/369858/thumb-givenchy-antigona-medium-model-bag-worn-on-the-shoulder-or-carried-in-the-hand-in-black-grained-leather.jpg",
    "condition": "Pre-Owned",
    "collection": "antigona",
    "color": "black",
    "material": "leather",
    "category": "handbag",
    "folder": "bag/givenchy/antigona",
    "size": "medium"
  },
  {
    "brand": "Givenchy",
    "href": "https://www.collectorsquare.com/en/bags/givenchy/nightingale/givenchy-nightingale-small-model-shoulder-bag-in-navy-blue-grained-leather-401421.html",
    "price": 5351.4,
    "trends": [
      {
        "date": "2024-05-18",
        "price": 5351.4
      },
      {
        "date": "2024-04-13",
        "price": 6170.0
      },
      {
        "date": "2024-03-23",
        "price": 6170.0
      }
    ],
    "title": "Givenchy Nightingale mini shoulder bag in dark blue grained leather",
    "like": 0,
    "source": "CollectorSquare",
    "url": "https://www.collectorsquare.com/en/bags/givenchy/nightingale/givenchy-nightingale-small-model-shoulder-bag-in-navy-blue-grained-leather-401421.html",
    "id": "collectorsquare-401421",
    "productId": "401421",
    "currency": "HKD",
    "image": "https://medias.collectorsquare.com/images/products/401421/thumb-givenchy-nightingale-mini-shoulder-bag-in-dark-blue-grained-leather.jpg",
    "condition": "Pre-Owned",
    "collection": "nightingale",
    "color": "blue",
    "material": "leather",
    "category": "shoulder bag",
    "folder": "bag/givenchy/nightingale",
    "size": "mini"
  },
  {
    "brand": "Givenchy",
    "href": "https://www.collectorsquare.com/en/bags/givenchy/shark/givenchy-shark-petit-modele-shoulder-bag-in-red-leather-341634.html",
    "price": 5153.2,
    "trends": [
      {
        "date": "2024-05-18",
        "price": 5153.2
      }
    ],
    "title": "Givenchy Shark Petit Modele shoulder bag in red leather",
    "like": 0,
    "source": "CollectorSquare",
    "url": "https://www.collectorsquare.com/en/bags/givenchy/shark/givenchy-shark-petit-modele-shoulder-bag-in-red-leather-341634.html",
    "id": "collectorsquare-341634",
    "productId": "341634",
    "currency": "HKD",
    "image": "https://medias.collectorsquare.com/images/products/341634/thumb-givenchy-shark-petit-modele-shoulder-bag-in-red-leather.jpg",
    "condition": "Pre-Owned",
    "collection": "shark",
    "color": "red",
    "material": "leather",
    "category": "shoulder bag",
    "folder": "bag/givenchy/shark",
    "size": null
  },
  {
    "brand": "Givenchy",
    "href": "https://www.collectorsquare.com/en/bags/givenchy/antigona/givenchy-antigona-small-model-shoulder-bag-in-black-leather-342835.html",
    "price": 8919.0,
    "trends": [
      {
        "date": "2024-05-18",
        "price": 8919.0
      }
    ],
    "title": "Givenchy Antigona small model shoulder bag in black leather",
    "like": 0,
    "source": "CollectorSquare",
    "url": "https://www.collectorsquare.com/en/bags/givenchy/antigona/givenchy-antigona-small-model-shoulder-bag-in-black-leather-342835.html",
    "id": "collectorsquare-342835",
    "productId": "342835",
    "currency": "HKD",
    "image": "https://medias.collectorsquare.com/images/products/342835/thumb-givenchy-antigona-small-model-shoulder-bag-in-black-leather.jpg",
    "condition": "Pre-Owned",
    "collection": "antigona",
    "color": "black",
    "material": "leather",
    "category": "shoulder bag",
    "folder": "bag/givenchy/antigona",
    "size": "small"
  },
  {
    "brand": "Givenchy",
    "href": "https://www.collectorsquare.com/en/bags/givenchy/lucrezia/givenchy-lucrezia-briefcase-in-red-grained-leather-338754.html",
    "price": 7036.1,
    "trends": [
      {
        "date": "2024-05-18",
        "price": 7036.1
      }
    ],
    "title": "Givenchy Lucrezia briefcase in red grained leather",
    "like": 0,
    "source": "CollectorSquare",
    "url": "https://www.collectorsquare.com/en/bags/givenchy/lucrezia/givenchy-lucrezia-briefcase-in-red-grained-leather-338754.html",
    "id": "collectorsquare-338754",
    "productId": "338754",
    "currency": "HKD",
    "image": "https://medias.collectorsquare.com/images/products/338754/thumb-givenchy-lucrezia-briefcase-in-red-grained-leather.jpg",
    "condition": "Pre-Owned",
    "collection": "lucrezia",
    "color": "red",
    "material": "leather",
    "category": "briefcase",
    "folder": "bag/givenchy/lucrezia",
    "size": null
  },
  {
    "brand": "Givenchy",
    "href": "https://www.collectorsquare.com/en/bags/givenchy/pandora/givenchy-mini-pandora-wallet-on-chain-shoulder-bag-in-black-gold-and-red-suede-354411.html",
    "price": 6045.1,
    "trends": [
      {
        "date": "2024-05-18",
        "price": 6045.1
      },
      {
        "date": "2024-04-13",
        "price": 5890.0
      },
      {
        "date": "2024-03-23",
        "price": 5890.0
      }
    ],
    "title": "Givenchy Mini Pandora Wallet On Chain shoulder bag in black, gold and red suede",
    "like": 0,
    "source": "CollectorSquare",
    "url": "https://www.collectorsquare.com/en/bags/givenchy/pandora/givenchy-mini-pandora-wallet-on-chain-shoulder-bag-in-black-gold-and-red-suede-354411.html",
    "id": "collectorsquare-354411",
    "productId": "354411",
    "currency": "HKD",
    "image": "https://medias.collectorsquare.com/images/products/354411/thumb-givenchy-mini-pandora-wallet-on-chain-shoulder-bag-in-black-gold-and-red-suede.jpg",
    "condition": "Pre-Owned",
    "collection": "pandora",
    "color": "black",
    "material": "leather",
    "category": "shoulder bag",
    "folder": "bag/givenchy/pandora",
    "size": "mini"
  },
  {
    "brand": "Givenchy",
    "href": "https://www.collectorsquare.com/en/bags/givenchy/nightingale/givenchy-nightingale-shoulder-bag-in-black-braided-leather-338773.html",
    "price": 7333.400000000001,
    "trends": [
      {
        "date": "2024-05-18",
        "price": 7333.400000000001
      }
    ],
    "title": "Givenchy Nightingale shoulder bag in black braided leather",
    "like": 0,
    "source": "CollectorSquare",
    "url": "https://www.collectorsquare.com/en/bags/givenchy/nightingale/givenchy-nightingale-shoulder-bag-in-black-braided-leather-338773.html",
    "id": "collectorsquare-338773",
    "productId": "338773",
    "currency": "HKD",
    "image": "https://medias.collectorsquare.com/images/products/338773/thumb-givenchy-nightingale-shoulder-bag-in-black-braided-leather.jpg",
    "condition": "Pre-Owned",
    "collection": "nightingale",
    "color": "black",
    "material": "leather",
    "category": "shoulder bag",
    "folder": "bag/givenchy/nightingale",
    "size": null
  },
  {
    "brand": "Givenchy",
    "href": "https://www.collectorsquare.com/en/bags/givenchy/nightingale/givenchy-nightingale-small-model-handbag-in-black-leather-342782.html",
    "price": 9216.3,
    "trends": [
      {
        "date": "2024-05-18",
        "price": 9216.3
      }
    ],
    "title": "Givenchy Nightingale small model handbag in black leather",
    "like": 0,
    "source": "CollectorSquare",
    "url": "https://www.collectorsquare.com/en/bags/givenchy/nightingale/givenchy-nightingale-small-model-handbag-in-black-leather-342782.html",
    "id": "collectorsquare-342782",
    "productId": "342782",
    "currency": "HKD",
    "image": "https://medias.collectorsquare.com/images/products/342782/thumb-givenchy-nightingale-small-model-handbag-in-black-leather.jpg",
    "condition": "Pre-Owned",
    "collection": "nightingale",
    "color": "black",
    "material": "leather",
    "category": "handbag",
    "folder": "bag/givenchy/nightingale",
    "size": "small"
  },
  {
    "brand": "Givenchy",
    "href": "https://www.collectorsquare.com/en/bags/givenchy/nightingale/givenchy-nightingale-handbag-in-black-grained-leather-342811.html",
    "price": 13576.7,
    "trends": [
      {
        "date": "2024-05-18",
        "price": 13576.7
      }
    ],
    "title": "Givenchy Nightingale handbag in black grained leather",
    "like": 0,
    "source": "CollectorSquare",
    "url": "https://www.collectorsquare.com/en/bags/givenchy/nightingale/givenchy-nightingale-handbag-in-black-grained-leather-342811.html",
    "id": "collectorsquare-342811",
    "productId": "342811",
    "currency": "HKD",
    "image": "https://medias.collectorsquare.com/images/products/342811/thumb-givenchy-nightingale-handbag-in-black-grained-leather.jpg",
    "condition": "Pre-Owned",
    "collection": "nightingale",
    "color": "black",
    "material": "leather",
    "category": "handbag",
    "folder": "bag/givenchy/nightingale",
    "size": null
  },
  {
    "brand": "Givenchy",
    "href": "https://www.collectorsquare.com/en/bags/givenchy/antigona/givenchy-antigona-medium-model-bag-worn-on-the-shoulder-or-carried-in-the-hand-in-black-grained-leather-352800.html",
    "price": 10801.9,
    "trends": [
      {
        "date": "2024-05-18",
        "price": 10801.9
      },
      {
        "date": "2024-04-13",
        "price": 10310.0
      },
      {
        "date": "2024-03-23",
        "price": 10310.0
      }
    ],
    "title": "Givenchy Antigona medium model bag worn on the shoulder or carried in the hand in black grained leather",
    "like": 0,
    "source": "CollectorSquare",
    "url": "https://www.collectorsquare.com/en/bags/givenchy/antigona/givenchy-antigona-medium-model-bag-worn-on-the-shoulder-or-carried-in-the-hand-in-black-grained-leather-352800.html",
    "id": "collectorsquare-352800",
    "productId": "352800",
    "currency": "HKD",
    "image": "https://medias.collectorsquare.com/images/products/352800/thumb-givenchy-antigona-medium-model-bag-worn-on-the-shoulder-or-carried-in-the-hand-in-black-grained-leather.jpg",
    "condition": "Pre-Owned",
    "collection": "antigona",
    "color": "black",
    "material": "leather",
    "category": "handbag",
    "folder": "bag/givenchy/antigona",
    "size": "medium"
  },
  {
    "brand": "Givenchy",
    "href": "https://www.collectorsquare.com/en/bags/givenchy/pandora/givenchy-pandora-mini-shoulder-bag-in-black-leather-370005.html",
    "price": 3964.0,
    "trends": [
      {
        "date": "2024-05-18",
        "price": 3964.0
      },
      {
        "date": "2024-04-13",
        "price": 3910.0
      },
      {
        "date": "2024-03-23",
        "price": 3910.0
      }
    ],
    "title": "Givenchy Pandora mini shoulder bag in black leather",
    "like": 0,
    "source": "CollectorSquare",
    "url": "https://www.collectorsquare.com/en/bags/givenchy/pandora/givenchy-pandora-mini-shoulder-bag-in-black-leather-370005.html",
    "id": "collectorsquare-370005",
    "productId": "370005",
    "currency": "HKD",
    "image": "https://medias.collectorsquare.com/images/products/370005/thumb-givenchy-pandora-mini-shoulder-bag-in-black-leather.jpg",
    "condition": "Pre-Owned",
    "collection": "pandora",
    "color": "black",
    "material": "leather",
    "category": "shoulder bag",
    "folder": "bag/givenchy/pandora",
    "size": "mini"
  }
]