[
  {
    "brand": "Goyard",
    "collection": "saigon",
    "price": 38961.0,
    "color": "black",
    "category": null,
    "material": null,
    "trends": [
      {
        "date": "2024-05-17",
        "price": 38961.0
      }
    ],
    "title": "Goyard Goyardine Structure Mini Saigon Black Gold",
    "like": 23,
    "source": "Fashionphile",
    "url": "https://www.fashionphile.com/p/goyard-goyardine-structure-mini-saigon-black-gold-1430765",
    "id": "fashionphile-1430765",
    "productId": "1430765",
    "currency": "HKD",
    "image": "https://prod-images.fashionphile.com/main/f0586c281b0bae9fde47a2f9b32475e2/4fe7ff22815fa6a8ab36ed15c45f0d5f.jpg",
    "folder": "bag/goyard/saigon",
    "condition": "Excellent",
    "size": "mini"
  },
  {
    "brand": "Goyard",
    "collection": "cap vert",
    "price": 17823.0,
    "color": "yellow",
    "category": null,
    "material": null,
    "trends": [
      {
        "date": "2024-05-17",
        "price": 17823.0
      }
    ],
    "title": "Goyard Goyardine Sac Cap Vert Yellow",
    "like": 32,
    "source": "Fashionphile",
    "url": "https://www.fashionphile.com/p/goyard-goyardine-sac-cap-vert-yellow-1424884",
    "id": "fashionphile-1424884",
    "productId": "1424884",
    "currency": "HKD",
    "image": "https://prod-images.fashionphile.com/main/970163b0a2b43826b4e942f1ee1496e3/a9ce2c1ec09b7c7c77aff4710c571fe5.jpg",
    "folder": "bag/goyard/cap vert",
    "condition": "Excellent",
    "size": null
  },
  {
    "brand": "Goyard",
    "collection": "saigon",
    "price": 40521.0,
    "color": "grey",
    "category": null,
    "material": null,
    "trends": [
      {
        "date": "2024-05-17",
        "price": 40521.0
      }
    ],
    "title": "Goyard Goyardine Saigon PM Grey",
    "like": 50,
    "source": "Fashionphile",
    "url": "https://www.fashionphile.com/p/goyard-goyardine-saigon-pm-grey-1427591",
    "id": "fashionphile-1427591",
    "productId": "1427591",
    "currency": "HKD",
    "image": "https://prod-images.fashionphile.com/main/18033840a9e3d6851703d9ccd89c3194/e5bb286c3f8ab93b4a9a113a8b2f26e4.jpg",
    "folder": "bag/goyard/saigon",
    "condition": "Excellent",
    "size": null
  },
  {
    "brand": "Goyard",
    "collection": "saigon",
    "price": 27261.0,
    "color": "silver",
    "category": null,
    "material": null,
    "trends": [
      {
        "date": "2024-05-17",
        "price": 27261.0
      }
    ],
    "title": "Goyard Goyardine Precious Metals Mini Saigon Silver",
    "like": 45,
    "source": "Fashionphile",
    "url": "https://www.fashionphile.com/p/goyard-goyardine-precious-metals-mini-saigon-silver-1428131",
    "id": "fashionphile-1428131",
    "productId": "1428131",
    "currency": "HKD",
    "image": "https://prod-images.fashionphile.com/main/8e50507181ba99108df69915fec1c05d/38e232bb5e6bf1e6cb5a2e2b7b03e4cc.jpg",
    "folder": "bag/goyard/saigon",
    "condition": "Excellent",
    "size": "mini"
  },
  {
    "brand": "Goyard",
    "collection": "saigon",
    "price": 37284.0,
    "color": "burgundy",
    "category": null,
    "material": null,
    "trends": [
      {
        "date": "2024-05-17",
        "price": 37284.0
      }
    ],
    "title": "Goyard Goyardine Mini Saigon Burgundy",
    "like": 87,
    "source": "Fashionphile",
    "url": "https://www.fashionphile.com/p/goyard-goyardine-mini-saigon-burgundy-1413052",
    "id": "fashionphile-1413052",
    "productId": "1413052",
    "currency": "HKD",
    "image": "https://prod-images.fashionphile.com/main/2fa313b38b251678a02e998ce539899f/8b6ccdc63cb81004b1c38650e05b2d96.jpg",
    "folder": "bag/goyard/saigon",
    "condition": "Excellent",
    "size": "mini"
  },
  {
    "brand": "Goyard",
    "collection": "saigon",
    "price": 28353.0,
    "color": "black",
    "category": null,
    "material": null,
    "trends": [
      {
        "date": "2024-05-17",
        "price": 28353.0
      }
    ],
    "title": "Goyard Goyardine Mini Saigon Black Gold",
    "like": 80,
    "source": "Fashionphile",
    "url": "https://www.fashionphile.com/p/goyard-goyardine-mini-saigon-black-gold-1424971",
    "id": "fashionphile-1424971",
    "productId": "1424971",
    "currency": "HKD",
    "image": "https://prod-images.fashionphile.com/main/264506e1c26f270e9c5c9f7d0f6b177e/18b956fc31f5e4385a6edb2e916e1102.jpg",
    "folder": "bag/goyard/saigon",
    "condition": "Excellent",
    "size": "mini"
  },
  {
    "brand": "Goyard",
    "collection": "saigon",
    "price": 38103.0,
    "color": "black",
    "category": null,
    "material": null,
    "trends": [
      {
        "date": "2024-05-17",
        "price": 38103.0
      }
    ],
    "title": "Goyard Goyardine Saigon PM Black",
    "like": 75,
    "source": "Fashionphile",
    "url": "https://www.fashionphile.com/p/goyard-goyardine-saigon-pm-black-1423927",
    "id": "fashionphile-1423927",
    "productId": "1423927",
    "currency": "HKD",
    "image": "https://prod-images.fashionphile.com/main/a86fcebe37c3e9c82e43c25d54ad2146/8f5ddc9c5e3049916d8677cd041ba482.jpg",
    "folder": "bag/goyard/saigon",
    "condition": "Excellent",
    "size": null
  },
  {
    "brand": "Goyard",
    "collection": "anjou",
    "price": 16341.0,
    "color": "black",
    "category": null,
    "material": null,
    "trends": [
      {
        "date": "2024-05-17",
        "price": 16341.0
      },
      {
        "date": "2024-04-13",
        "price": 16341.0
      }
    ],
    "title": "Goyard Goyardine Reversible Anjou PM Black Gold",
    "like": 35,
    "source": "Fashionphile",
    "url": "https://www.fashionphile.com/p/goyard-goyardine-reversible-anjou-pm-black-gold-1404140",
    "id": "fashionphile-1404140",
    "productId": "1404140",
    "currency": "HKD",
    "image": "https://prod-images.fashionphile.com/main/431a0d45c0621fbe292a88f6ece939f2/6128a3bcdffa5eec89ac3909c628c307.jpg",
    "folder": "bag/goyard/anjou",
    "condition": "Very Good",
    "size": null
  },
  {
    "brand": "Goyard",
    "collection": "anjou",
    "price": 22659.0,
    "color": "white",
    "category": null,
    "material": null,
    "trends": [
      {
        "date": "2024-05-17",
        "price": 22659.0
      }
    ],
    "title": "Goyard Goyardine Reversible Mini Anjou White",
    "like": 47,
    "source": "Fashionphile",
    "url": "https://www.fashionphile.com/p/goyard-goyardine-reversible-mini-anjou-white-1415546",
    "id": "fashionphile-1415546",
    "productId": "1415546",
    "currency": "HKD",
    "image": "https://prod-images.fashionphile.com/main/450a939eb6393fef77fb1084f39c6df8/c77cabb89ad3c7f3bb74e54adeef7413.jpg",
    "folder": "bag/goyard/anjou",
    "condition": "Excellent",
    "size": "mini"
  },
  {
    "brand": "Goyard",
    "collection": "saigon",
    "price": 27768.0,
    "color": "yellow",
    "category": null,
    "material": null,
    "trends": [
      {
        "date": "2024-05-17",
        "price": 27768.0
      },
      {
        "date": "2024-04-13",
        "price": 29250.0
      },
      {
        "date": "2024-03-07",
        "price": 27768.0
      }
    ],
    "title": "Goyard Goyardine Mini Saigon Yellow",
    "like": 204,
    "source": "Fashionphile",
    "url": "https://www.fashionphile.com/p/goyard-goyardine-mini-saigon-yellow-1315142",
    "id": "fashionphile-1315142",
    "productId": "1315142",
    "currency": "HKD",
    "image": "https://prod-images.fashionphile.com/main/85679c6c984c0c232c85eb52b0b3d929/9dd851b640cc6057d7c2797a6c96ddf5.jpg",
    "folder": "bag/goyard/saigon",
    "condition": "Excellent",
    "size": "mini"
  },
  {
    "brand": "Goyard",
    "collection": "anjou",
    "price": 25779.0,
    "color": "black",
    "category": null,
    "material": null,
    "trends": [
      {
        "date": "2024-05-17",
        "price": 25779.0
      },
      {
        "date": "2024-04-13",
        "price": 27144.0
      }
    ],
    "title": "Goyard Goyardine Reversible Mini Anjou Black",
    "like": 64,
    "source": "Fashionphile",
    "url": "https://www.fashionphile.com/p/goyard-goyardine-reversible-mini-anjou-black-1410417",
    "id": "fashionphile-1410417",
    "productId": "1410417",
    "currency": "HKD",
    "image": "https://prod-images.fashionphile.com/main/0dddf879f68293ee618bc1d642ba16c0/687e890ffd330fe181c65af8f0177884.jpg",
    "folder": "bag/goyard/anjou",
    "condition": "New",
    "size": "mini"
  },
  {
    "brand": "Goyard",
    "collection": "saigon",
    "price": 38103.0,
    "color": "black",
    "category": null,
    "material": null,
    "trends": [
      {
        "date": "2024-05-17",
        "price": 38103.0
      },
      {
        "date": "2024-04-13",
        "price": 40092.0
      },
      {
        "date": "2024-03-07",
        "price": 40092.0
      }
    ],
    "title": "Goyard Goyardine Saigon PM Black",
    "like": 157,
    "source": "Fashionphile",
    "url": "https://www.fashionphile.com/p/goyard-goyardine-saigon-pm-black-1366693",
    "id": "fashionphile-1366693",
    "productId": "1366693",
    "currency": "HKD",
    "image": "https://prod-images.fashionphile.com/main/e2b4eac68909b47160da6da7cc676091/fed24b86ad103f5760ba8e35a0a87abb.jpg",
    "folder": "bag/goyard/saigon",
    "condition": "Excellent",
    "size": null
  },
  {
    "brand": "Goyard",
    "collection": "anjou",
    "price": 22152.0,
    "color": "black",
    "category": null,
    "material": null,
    "trends": [
      {
        "date": "2024-05-17",
        "price": 22152.0
      },
      {
        "date": "2024-04-13",
        "price": 23322.0
      }
    ],
    "title": "Goyard Goyardine Reversible Mini Anjou Black",
    "like": 81,
    "source": "Fashionphile",
    "url": "https://www.fashionphile.com/p/goyard-goyardine-reversible-mini-anjou-black-1406736",
    "id": "fashionphile-1406736",
    "productId": "1406736",
    "currency": "HKD",
    "image": "https://prod-images.fashionphile.com/main/566cbb1f11a1142512a4c67bc5bf4f5f/78ea39c655564b86cbc24aeefba66688.jpg",
    "folder": "bag/goyard/anjou",
    "condition": "Excellent",
    "size": "mini"
  },
  {
    "brand": "Goyard",
    "collection": "anjou",
    "price": 19422.0,
    "color": "burgundy",
    "category": null,
    "material": null,
    "trends": [
      {
        "date": "2024-05-17",
        "price": 19422.0
      },
      {
        "date": "2024-04-13",
        "price": 20436.0
      },
      {
        "date": "2024-03-07",
        "price": 18408.0
      }
    ],
    "title": "Goyard Goyardine Reversible Anjou GM Burgundy",
    "like": 99,
    "source": "Fashionphile",
    "url": "https://www.fashionphile.com/p/goyard-goyardine-reversible-anjou-gm-burgundy-1353913",
    "id": "fashionphile-1353913",
    "productId": "1353913",
    "currency": "HKD",
    "image": "https://prod-images.fashionphile.com/main/5fb27df212a16b3f7b12bd026ee199ce/655358bae4bc552deb9a254f90ac37dc.jpg",
    "folder": "bag/goyard/anjou",
    "condition": "Very Good",
    "size": null
  },
  {
    "brand": "Goyard",
    "collection": "anjou",
    "price": 19422.0,
    "color": "white",
    "category": null,
    "material": null,
    "trends": [
      {
        "date": "2024-05-17",
        "price": 19422.0
      },
      {
        "date": "2024-04-13",
        "price": 20436.0
      }
    ],
    "title": "Goyard Goyardine Reversible Mini Anjou White",
    "like": 69,
    "source": "Fashionphile",
    "url": "https://www.fashionphile.com/p/goyard-goyardine-reversible-mini-anjou-white-1404774",
    "id": "fashionphile-1404774",
    "productId": "1404774",
    "currency": "HKD",
    "image": "https://prod-images.fashionphile.com/main/8741539d1a483111fa4072f0837a23e2/2447238eda1a8a35a8c6fec5136db5a1.jpg",
    "folder": "bag/goyard/anjou",
    "condition": "Excellent",
    "size": "mini"
  },
  {
    "brand": "Goyard",
    "collection": "saigon",
    "price": 46644.0,
    "color": "red",
    "category": null,
    "material": null,
    "trends": [
      {
        "date": "2024-05-17",
        "price": 46644.0
      },
      {
        "date": "2024-04-13",
        "price": 49101.0
      },
      {
        "date": "2024-03-07",
        "price": 44187.0
      }
    ],
    "title": "Goyard Goyardine Saigon PM Red",
    "like": 148,
    "source": "Fashionphile",
    "url": "https://www.fashionphile.com/p/goyard-goyardine-saigon-pm-red-1345514",
    "id": "fashionphile-1345514",
    "productId": "1345514",
    "currency": "HKD",
    "image": "https://prod-images.fashionphile.com/main/bb426ffd59414d200a96f9afcba3e601/5378408a582619512b3d518a3483a93e.jpg",
    "folder": "bag/goyard/saigon",
    "condition": "Excellent",
    "size": null
  },
  {
    "brand": "Goyard",
    "collection": "anjou",
    "price": 23985.0,
    "color": "black",
    "category": null,
    "material": null,
    "trends": [
      {
        "date": "2024-05-17",
        "price": 23985.0
      },
      {
        "date": "2024-04-13",
        "price": 26637.0
      }
    ],
    "title": "Goyard Goyardine Reversible Mini Anjou Black Gold",
    "like": 140,
    "source": "Fashionphile",
    "url": "https://www.fashionphile.com/p/goyard-goyardine-reversible-mini-anjou-black-gold-1338647",
    "id": "fashionphile-1338647",
    "productId": "1338647",
    "currency": "HKD",
    "image": "https://prod-images.fashionphile.com/main/848f0f2fb0d6b1646ed01b144eec7548/6c82853d1e932d54dffc254c412c056b.jpg",
    "folder": "bag/goyard/anjou",
    "condition": "New",
    "size": "mini"
  },
  {
    "brand": "Goyard",
    "collection": "saigon",
    "price": 30732.0,
    "color": "green",
    "category": null,
    "material": null,
    "trends": [
      {
        "date": "2024-05-17",
        "price": 30732.0
      },
      {
        "date": "2024-04-13",
        "price": 34164.0
      }
    ],
    "title": "Goyard Goyardine Saigon PM Green",
    "like": 83,
    "source": "Fashionphile",
    "url": "https://www.fashionphile.com/p/goyard-goyardine-saigon-pm-green-1401021",
    "id": "fashionphile-1401021",
    "productId": "1401021",
    "currency": "HKD",
    "image": "https://prod-images.fashionphile.com/main/964105ca2127913c9d90b96f3635d8ea/5eeaf00e5b972d4fc07aada24456d83b.jpg",
    "folder": "bag/goyard/saigon",
    "condition": "Very Good",
    "size": null
  },
  {
    "brand": "Goyard",
    "collection": "anjou",
    "price": 21762.0,
    "color": "black",
    "category": null,
    "material": null,
    "trends": [
      {
        "date": "2024-05-17",
        "price": 21762.0
      },
      {
        "date": "2024-04-13",
        "price": 24180.0
      },
      {
        "date": "2024-03-07",
        "price": 21762.0
      }
    ],
    "title": "Goyard Goyardine Reversible Mini Anjou Black Gold",
    "like": 248,
    "source": "Fashionphile",
    "url": "https://www.fashionphile.com/p/goyard-goyardine-reversible-mini-anjou-black-gold-1327846",
    "id": "fashionphile-1327846",
    "productId": "1327846",
    "currency": "HKD",
    "image": "https://prod-images.fashionphile.com/main/4b4f7ddba20716c6e586fc6a7568760d/9e15d4de57881b8ffadc1ee36d6d87d0.jpg",
    "folder": "bag/goyard/anjou",
    "condition": "Excellent",
    "size": "mini"
  },
  {
    "brand": "Goyard",
    "collection": "cap vert",
    "price": 18408.0,
    "color": "yellow",
    "category": null,
    "material": null,
    "trends": [
      {
        "date": "2024-05-17",
        "price": 18408.0
      },
      {
        "date": "2024-04-13",
        "price": 20475.0
      }
    ],
    "title": "Goyard Goyardine Sac Cap Vert Yellow",
    "like": 66,
    "source": "Fashionphile",
    "url": "https://www.fashionphile.com/p/goyard-goyardine-sac-cap-vert-yellow-1399885",
    "id": "fashionphile-1399885",
    "productId": "1399885",
    "currency": "HKD",
    "image": "https://prod-images.fashionphile.com/main/8268ace428fb6aac5065c5e8f72e22c4/93049f1e7565e74f8460fdd739178ef9.jpg",
    "folder": "bag/goyard/cap vert",
    "condition": "Very Good",
    "size": null
  },
  {
    "brand": "Goyard",
    "collection": "saigon",
    "price": 39780.0,
    "color": "blue",
    "category": null,
    "material": null,
    "trends": [
      {
        "date": "2024-05-17",
        "price": 39780.0
      },
      {
        "date": "2024-04-13",
        "price": 44187.0
      }
    ],
    "title": "Goyard Goyardine Saigon PM Light Blue",
    "like": 104,
    "source": "Fashionphile",
    "url": "https://www.fashionphile.com/p/goyard-goyardine-saigon-pm-light-blue-1391453",
    "id": "fashionphile-1391453",
    "productId": "1391453",
    "currency": "HKD",
    "image": "https://prod-images.fashionphile.com/main/2da109285ee6bff0bafd013737fe255a/3d49bff7c47344d629365a3497e1e25a.jpg",
    "folder": "bag/goyard/saigon",
    "condition": "Excellent",
    "size": null
  },
  {
    "brand": "Goyard",
    "collection": "saigon",
    "price": 32409.0,
    "color": "black",
    "category": null,
    "material": null,
    "trends": [
      {
        "date": "2024-05-17",
        "price": 32409.0
      },
      {
        "date": "2024-04-13",
        "price": 35997.0
      }
    ],
    "title": "Goyard Goyardine Saigon PM Black",
    "like": 263,
    "source": "Fashionphile",
    "url": "https://www.fashionphile.com/p/goyard-goyardine-saigon-pm-black-1340698",
    "id": "fashionphile-1340698",
    "productId": "1340698",
    "currency": "HKD",
    "image": "https://prod-images.fashionphile.com/main/7000567a1e1ed64b5918e48d1e50ab48/a4f8eb52971d8d767b6ae0020758fd9b.jpg",
    "folder": "bag/goyard/saigon",
    "condition": "Excellent",
    "size": null
  },
  {
    "brand": "Goyard",
    "collection": "saigon",
    "price": 27222.0,
    "color": "yellow",
    "category": null,
    "material": null,
    "trends": [
      {
        "date": "2024-05-17",
        "price": 27222.0
      }
    ],
    "title": "Goyard Goyardine Mini Saigon Yellow",
    "like": 269,
    "source": "Fashionphile",
    "url": "https://www.fashionphile.com/p/goyard-goyardine-mini-saigon-yellow-1308424",
    "id": "fashionphile-1308424",
    "productId": "1308424",
    "currency": "HKD",
    "image": "https://prod-images.fashionphile.com/main/cf8b04a99fb8c70dd2d36e9e53b9bfb6/0d8586740af34e350cb45dcae35787a9.jpg",
    "folder": "bag/goyard/saigon",
    "condition": "Excellent",
    "size": "mini"
  }
]